pyproject.toml
survivalist_gamedata/__init__.py
survivalist_gamedata/__main__.py
survivalist_gamedata/common.py
survivalist_gamedata/config.py
survivalist_gamedata/config_default.yaml
survivalist_gamedata/items.py
survivalist_gamedata/logging.yaml
survivalist_gamedata/recipes.py
survivalist_gamedata-1.0.0.dist-info/entry_points.txt
survivalist_gamedata-1.0.0.dist-info/LICENSE.txt
survivalist_gamedata-1.0.0.dist-info/METADATA
survivalist_gamedata-1.0.0.dist-info/WHEEL
survivalist_gamedata-1.0.0.dist-info/RECORD
