Metadata-Version: 2.1
Name: survivalist-gamedata
Version: 1.0.0
Summary: Utility for extracting information about Survivalist: Invisible Strain from the game's XML files and saving it in CSV and Steam Community markup formats.
Home-page: https://github.com/rbscholtus/survivalist-gamedata
License: Apache-2.0
Author: Barend Scholtus
Author-email: barend.scholtus@gmail.com
Requires-Python: >=3.12,<4.0
Classifier: Development Status :: 5 - Production/Stable
Classifier: Environment :: Console
Classifier: Intended Audience :: Developers
Classifier: License :: OSI Approved :: Apache Software License
Classifier: Operating System :: OS Independent
Classifier: Programming Language :: Python :: 3
Classifier: Programming Language :: Python :: 3.12
Classifier: Topic :: Text Processing :: Markup :: XML
Classifier: Topic :: Utilities
Requires-Dist: attrdict (>=2.0.1,<3.0.0)
Requires-Dist: confuse (>=2.0.1,<3.0.0)
Requires-Dist: toml (>=0.10.2,<0.11.0)
Requires-Dist: xmltodict (>=0.13.0,<0.14.0)
Project-URL: Repository, https://github.com/rbscholtus/survivalist-gamedata
